MANIFEST.in
README.rst
setup.py
docs/HISTORY.txt
docs/LICENSE.GPL
docs/LICENSE.txt
ftw/__init__.py
ftw.quota.egg-info/PKG-INFO
ftw.quota.egg-info/SOURCES.txt
ftw.quota.egg-info/dependency_links.txt
ftw.quota.egg-info/entry_points.txt
ftw.quota.egg-info/namespace_packages.txt
ftw.quota.egg-info/not-zip-safe
ftw.quota.egg-info/requires.txt
ftw.quota.egg-info/top_level.txt
ftw/quota/__init__.py
ftw/quota/adapters.py
ftw/quota/configure.zcml
ftw/quota/extender.py
ftw/quota/handlers.py
ftw/quota/interfaces.py
ftw/quota/testing.py
ftw/quota/locales/ftw.quota.pot
ftw/quota/locales/de/LC_MESSAGES/ftw.quota.po
ftw/quota/tests/__init__.py
ftw/quota/tests/quota.txt
ftw/quota/tests/test.zcml
ftw/quota/tests/test_adapters.py
ftw/quota/tests/test_extender.py
ftw/quota/tests/test_functional_doctests.py
ftw/quota/tests/test_handlers.py