Metadata-Version: 1.0
Name: ftw.quota
Version: 1.0
Summary: Quota support for archetypes containers.
Home-page: https://github.com/4teamwork/ftw.quota/
Author: 4teamwork GmbH
Author-email: mailto:info@4teamwork.ch
License: GPL2
Keywords: ftw quota plone
Platform: UNKNOWN
Classifier: Framework :: Plone
Classifier: Framework :: Plone :: 4.0
Classifier: Framework :: Plone :: 4.1
Classifier: License :: OSI Approved :: GNU General Public License (GPL)
Classifier: Programming Language :: Python
Classifier: Programming Language :: Python :: 2.6
